starlette_json/__init__.py
starlette_json/starlette_orjson.py
starlette_json/starlette_rapidjson.py
starlette_json/starlette_simplejson.py
starlette_json/starlette_ujson.py
starlette_json-20.9.18.dist-info/LICENSE.md
starlette_json-20.9.18.dist-info/METADATA
starlette_json-20.9.18.dist-info/WHEEL
starlette_json-20.9.18.dist-info/top_level.txt
starlette_json-20.9.18.dist-info/RECORD
