Metadata-Version: 2.1
Name: starlette-json
Version: 20.9.18
Summary: Custom json serializers for the Starlette web framework.
Home-page: https://github.com/chrisliveseer/starlette-json
Author: Chris Liveseer
Author-email: chris@liveseer.com
License: BSD
Keywords: starlette json ujson orjson rapidjson
Platform: any
Classifier: License :: OSI Approved :: BSD License
Classifier: Programming Language :: Python
Classifier: Programming Language :: Python :: 3
Classifier: Programming Language :: Python :: 3.6
Classifier: Programming Language :: Python :: 3.7
Classifier: Programming Language :: Python :: 3.8
Classifier: Programming Language :: Python :: Implementation :: CPython
Requires-Python: >=3.6.0
Requires-Dist: starlette
